ebtelplusplus/high_level.py
ebtelplusplus/models.py
ebtelplusplus/_core.cpython-313-darwin.so
ebtelplusplus/_version.py
ebtelplusplus/__init__.py
ebtelplusplus/_low_level.py
ebtelplusplus/tests/conftest.py
ebtelplusplus/tests/__init__.py
ebtelplusplus/tests/test_rad_loss.py
ebtelplusplus/tests/test_single_fluid.py
ebtelplusplus/tests/test_solver.py
ebtelplusplus/tests/helpers.py
ebtelplusplus/tests/test_compare_idl.py
ebtelplusplus/tests/test_compare_hydrad.py
ebtelplusplus/tests/data/hydrad_single_tau500.txt
ebtelplusplus/tests/data/hydrad_electron_tau500.txt
ebtelplusplus/tests/data/hydrad_electron_tau200.txt
ebtelplusplus/tests/data/idl_area_expansion_A_c=3_A_0=1_A_tr=1.txt
ebtelplusplus/tests/data/hydrad_single_tau200.txt
ebtelplusplus/tests/data/hydrad_ion_tau200.txt
ebtelplusplus/tests/data/idl_single_event.txt
ebtelplusplus/tests/data/idl_area_expansion_A_c=3_A_0=2_A_tr=1.txt
ebtelplusplus/tests/data/idl_area_expansion_A_c=1_A_0=1_A_tr=1.txt
ebtelplusplus/tests/data/hydrad_ion_tau500.txt
ebtelplusplus/extern/heater.h
ebtelplusplus/extern/loop.cpp
ebtelplusplus/extern/helper.h
ebtelplusplus/extern/dem.h
ebtelplusplus/extern/observer.h
ebtelplusplus/extern/misc.cpp
ebtelplusplus/extern/misc.h
ebtelplusplus/extern/dem.cpp
ebtelplusplus/extern/observer.cpp
ebtelplusplus/extern/ebtel.cpp
ebtelplusplus/extern/constants.h
ebtelplusplus/extern/loop.h
ebtelplusplus/extern/heater.cpp
ebtelplusplus/data/__init__.py
ebtelplusplus/data/radiation/abund_30_rad_loss.dat
ebtelplusplus/data/radiation/abund_25_rad_loss.dat
ebtelplusplus/data/radiation/abund_15_rad_loss.dat
ebtelplusplus/data/radiation/abund_40_rad_loss.dat
ebtelplusplus/data/radiation/abund_10_rad_loss.dat
ebtelplusplus/data/radiation/abund_35_rad_loss.dat
ebtelplusplus/data/radiation/abund_20_rad_loss.dat
ebtelplusplus-0.5.0.dist-info/RECORD
ebtelplusplus-0.5.0.dist-info/WHEEL
ebtelplusplus-0.5.0.dist-info/METADATA
ebtelplusplus-0.5.0.dist-info/licenses/LICENSE
