Metadata-Version: 2.1
Name: ebtelplusplus
Version: 0.5.0
Summary: Zero-dimensional hydrodynamics of coronal loops
Keywords: heliophysics,solar physics,astrophysics,hydrodynamics,plasma physics,science
Author-Email: Will Barnes <will.t.barnes@gmail.com>
License:                     GNU GENERAL PUBLIC LICENSE
Classifier: Development Status :: 4 - Beta
Classifier: Intended Audience :: Science/Research
Classifier: License :: OSI Approved :: GNU General Public License v3 (GPLv3)
Classifier: Operating System :: MacOS :: MacOS X
Classifier: Operating System :: Microsoft :: Windows
Classifier: Operating System :: POSIX :: Linux
Classifier: Programming Language :: Python :: 3
Classifier: Programming Language :: Python :: 3.11
Classifier: Programming Language :: Python :: 3.12
Classifier: Programming Language :: Python :: 3.13
Classifier: Programming Language :: Python :: Implementation :: CPython
Classifier: Topic :: Scientific/Engineering :: Astronomy
Classifier: Topic :: Scientific/Engineering :: Physics
Project-URL: Homepage, https://github.com/rice-solar-physics/ebtelplusplus
Project-URL: Bug Tracker, https://github.com/rice-solar-physics/ebtelplusplus/issues
Project-URL: Discussions, https://github.com/rice-solar-physics/ebtelplusplus/discussions
Project-URL: Changelog, https://github.com/rice-solar-physics/ebtelplusplus/releases
Requires-Python: >=3.11
Requires-Dist: astropy
Provides-Extra: all
Requires-Dist: ebtelplusplus; extra == "all"
Provides-Extra: test
Requires-Dist: ebtelplusplus[all]; extra == "test"
Requires-Dist: hissw; extra == "test"
Requires-Dist: pytest>=6; extra == "test"
Requires-Dist: pytest-astropy; extra == "test"
Requires-Dist: pytest-cov>=3; extra == "test"
Provides-Extra: docs
Requires-Dist: ebtelplusplus[all]; extra == "docs"
Requires-Dist: matplotlib; extra == "docs"
Requires-Dist: pydata-sphinx-theme; extra == "docs"
Requires-Dist: sphinx-automodapi; extra == "docs"
Requires-Dist: sphinx-copybutton; extra == "docs"
Requires-Dist: sphinx-design; extra == "docs"
Requires-Dist: sphinx-gallery; extra == "docs"
Requires-Dist: sphinx>=7.0; extra == "docs"
Requires-Dist: sphinxcontrib-bibtex; extra == "docs"
Provides-Extra: dev
Requires-Dist: ebtelplusplus[docs,test]; extra == "dev"
